<PAMDataset>
  <Metadata>
    <MDI key="DataType">Generic</MDI>
  </Metadata>
  <PAMRasterBand band="1">
    <Histograms>
      <HistItem>
        <HistMin>-0.5</HistMin>
        <HistMax>166.5</HistMax>
        <BucketCount>167</BucketCount>
        <IncludeOutOfRange>1</IncludeOutOfRange>
        <Approximate>0</Approximate>
        <HistCounts>4535499|408|250|1086|1846|1194|2322|2462|2584|2155|2651|2850|2599|2907|2952|2930|2656|2696|2604|2411|2441|2225|2038|1866|1796|1641|1495|1421|1356|1277|1097|1087|1142|1002|1000|930|961|939|946|886|880|889|845|852|728|814|839|761|764|757|771|811|757|761|768|801|694|729|746|740|711|703|717|743|706|707|706|729|684|717|746|782|756|786|847|986|1203|1567|2152|2647|3620|4667|6220|7940|9604|11249|13017|15291|18581|21145|24989|30863|39516|47318|52556|55165|60323|69205|84082|91441|96502|97088|96052|95899|97346|98560|106275|123481|148006|161829|163672|163796|163765|165164|166413|168793|173089|180348|182506|186071|191438|205613|223100|242057|252713|265114|279005|291364|299164|300857|302678|311079|303654|287323|278683|281157|275449|257364|221654|173579|126493|80246|47918|25774|15135|9698|6125|3416|1860|947|577|319|251|164|129|72|38|37|29|14|8|8|5|8|1|2|3</HistCounts>
      </HistItem>
    </Histograms>
    <Metadata>
      <MDI key="RepresentationType">ATHEMATIC</MDI>
      <MDI key="STATISTICS_COVARIANCES">3394.145570877178,3145.040527578815,3263.403326242565</MDI>
      <MDI key="STATISTICS_EXCLUDEDVALUES"></MDI>
      <MDI key="STATISTICS_MAXIMUM">166</MDI>
      <MDI key="STATISTICS_MEAN">80.640478516759</MDI>
      <MDI key="STATISTICS_MINIMUM">0</MDI>
      <MDI key="STATISTICS_SKIPFACTORX">1</MDI>
      <MDI key="STATISTICS_SKIPFACTORY">1</MDI>
      <MDI key="STATISTICS_STDDEV">58.259296003961</MDI>
    </Metadata>
  </PAMRasterBand>
  <PAMRasterBand band="2">
    <Histograms>
      <HistItem>
        <HistMin>-0.5</HistMin>
        <HistMax>155.5</HistMax>
        <BucketCount>156</BucketCount>
        <IncludeOutOfRange>1</IncludeOutOfRange>
        <Approximate>0</Approximate>
        <HistCounts>4558763|2933|2784|2650|2512|2414|2337|2319|2161|2073|2070|2056|1904|1709|1720|1619|1530|1375|1366|1232|1092|1119|1059|1060|957|949|946|973|960|946|945|900|889|895|901|931|938|929|910|924|910|936|988|1008|1011|1072|1064|1094|1042|1027|1063|993|999|994|984|939|905|984|934|1012|1031|1004|1030|1151|1230|1553|1921|2305|2870|3322|3919|4369|5269|6442|7844|9537|10589|12379|14223|16701|19488|22316|26222|31107|37390|41797|45345|49445|54884|61409|69228|77971|87338|95828|100275|100438|99019|100804|106638|118765|135165|151949|170668|188057|195959|193973|189955|192016|201086|209794|217419|225716|237952|251586|266791|277302|292822|299491|301984|294148|284246|280033|281326|271156|253619|247254|251516|253947|243148|220926|181262|135196|90138|53624|29435|16829|10296|6504|3876|2046|1060|532|287|179|104|75|40|23|23|14|10|7|1|6|2|1</HistCounts>
      </HistItem>
    </Histograms>
    <Metadata>
      <MDI key="RepresentationType">ATHEMATIC</MDI>
      <MDI key="STATISTICS_COVARIANCES">3145.040527578815,2933.63944568547,3044.835701394437</MDI>
      <MDI key="STATISTICS_EXCLUDEDVALUES"></MDI>
      <MDI key="STATISTICS_MAXIMUM">155</MDI>
      <MDI key="STATISTICS_MEAN">74.664308029994</MDI>
      <MDI key="STATISTICS_MINIMUM">0</MDI>
      <MDI key="STATISTICS_SKIPFACTORX">1</MDI>
      <MDI key="STATISTICS_SKIPFACTORY">1</MDI>
      <MDI key="STATISTICS_STDDEV">54.16308194412</MDI>
    </Metadata>
  </PAMRasterBand>
  <PAMRasterBand band="3">
    <Histograms>
      <HistItem>
        <HistMin>-0.5</HistMin>
        <HistMax>158.5</HistMax>
        <BucketCount>159</BucketCount>
        <IncludeOutOfRange>1</IncludeOutOfRange>
        <Approximate>0</Approximate>
        <HistCounts>4540022|1343|2456|1786|2713|3152|2558|3094|2840|3132|2817|2895|2705|2645|2527|2491|2324|2066|1989|1869|1722|1641|1488|1461|1410|1396|1213|1145|1069|1005|1032|970|962|914|940|900|923|927|895|892|868|915|905|853|829|813|852|863|913|874|928|907|914|917|985|955|904|985|1052|1089|1045|1089|1103|1043|1060|1118|1076|1065|1023|1038|1001|1001|1047|1086|1061|1120|1124|1231|1370|1623|1927|2173|2591|3028|3322|3389|3713|4316|5098|6427|8061|9948|11552|14126|16727|19612|22309|25668|29735|35353|41831|50389|58190|66990|75637|86730|101122|118534|135969|154562|173449|195590|220374|249624|277911|310803|337324|361601|377265|394664|412463|437270|450222|459283|452960|441501|420361|392667|344889|286723|230025|174105|135091|101842|80389|61653|48319|35953|25684|18478|12551|6375|3234|1519|706|371|184|116|51|28|12|22|8|4|4|6|1|0|1</HistCounts>
      </HistItem>
    </Histograms>
    <Metadata>
      <MDI key="RepresentationType">ATHEMATIC</MDI>
      <MDI key="STATISTICS_COVARIANCES">3263.403326242565,3044.835701394437,3232.090321551016</MDI>
      <MDI key="STATISTICS_EXCLUDEDVALUES"></MDI>
      <MDI key="STATISTICS_MAXIMUM">158</MDI>
      <MDI key="STATISTICS_MEAN">79.298697087107</MDI>
      <MDI key="STATISTICS_MINIMUM">0</MDI>
      <MDI key="STATISTICS_SKIPFACTORX">1</MDI>
      <MDI key="STATISTICS_SKIPFACTORY">1</MDI>
      <MDI key="STATISTICS_STDDEV">56.851475983927</MDI>
    </Metadata>
  </PAMRasterBand>
</PAMDataset>
