<PAMDataset>
  <Metadata>
    <MDI key="DataType">Generic</MDI>
  </Metadata>
  <PAMRasterBand band="1">
    <Histograms>
      <HistItem>
        <HistMin>-0.5</HistMin>
        <HistMax>207.5</HistMax>
        <BucketCount>208</BucketCount>
        <IncludeOutOfRange>1</IncludeOutOfRange>
        <Approximate>0</Approximate>
        <HistCounts>2200182|661|405|1844|3154|2353|3517|3567|3667|4231|4798|5539|6650|7629|8341|8895|9560|9884|9745|9863|9656|9804|9863|10099|10153|10583|11133|11417|12084|12441|12671|12728|12911|13117|13336|13596|13608|13411|13410|13597|13480|13258|13478|13089|13151|13599|13581|13836|13896|14133|14527|14422|14786|14739|15128|15375|15748|16153|16129|16255|16535|16748|17192|17615|17748|17805|18417|18580|18836|19366|19603|20553|20640|21589|22289|23129|24180|25269|26635|27998|29982|30950|32631|34437|36200|37775|39461|40445|41273|42354|44397|45624|47354|49369|51180|52485|53211|54387|57852|61668|66115|70835|75592|82665|89302|96397|105953|118144|130912|141276|149229|156889|162205|167289|177950|188690|202124|217931|230908|242440|257008|272569|301197|330940|364689|391339|410933|420878|438348|455808|460675|450344|436944|426014|422087|433498|450109|478472|504179|526532|531756|526192|514636|490619|461030|416304|358136|292250|232047|175779|129002|96747|77410|64937|57122|50060|43121|36715|31052|25722|21350|17875|14743|11914|9515|7735|5972|4848|3853|3122|2608|2146|1807|1501|1387|1224|1050|927|849|766|647|565|474|397|351|270|241|193|160|124|136|109|83|53|41|29|26|25|18|9|12|14|4|3|2|3|0|1</HistCounts>
      </HistItem>
    </Histograms>
    <Metadata>
      <MDI key="RepresentationType">ATHEMATIC</MDI>
      <MDI key="STATISTICS_COVARIANCES">2054.970442893575,1992.541930324777,1995.674336560615</MDI>
      <MDI key="STATISTICS_EXCLUDEDVALUES"></MDI>
      <MDI key="STATISTICS_MAXIMUM">207</MDI>
      <MDI key="STATISTICS_MEAN">110.90403517588</MDI>
      <MDI key="STATISTICS_MINIMUM">0</MDI>
      <MDI key="STATISTICS_SKIPFACTORX">1</MDI>
      <MDI key="STATISTICS_SKIPFACTORY">1</MDI>
      <MDI key="STATISTICS_STDDEV">45.33178181909</MDI>
    </Metadata>
  </PAMRasterBand>
  <PAMRasterBand band="2">
    <Histograms>
      <HistItem>
        <HistMin>-0.5</HistMin>
        <HistMax>204.5</HistMax>
        <BucketCount>205</BucketCount>
        <IncludeOutOfRange>1</IncludeOutOfRange>
        <Approximate>0</Approximate>
        <HistCounts>2213126|3821|4014|4047|4487|5043|5624|6251|7088|8238|9620|11050|12069|12437|12746|12678|12670|12521|12397|12683|12900|13048|13350|13645|13965|14184|14310|14127|14721|14625|14708|14308|14338|13942|14087|13989|14017|13957|14508|14131|14297|14574|14681|14939|15160|15451|15587|15906|15971|16502|16510|17002|16877|17475|17778|17975|18224|18451|18634|19206|19489|19719|20051|20656|20853|21226|21792|22421|23035|23529|24540|25306|26047|27270|28344|29783|30788|32192|32707|33939|35180|36894|38488|39651|41559|43169|44339|45196|45640|47352|49518|51865|55261|58800|62918|65898|67502|69191|72780|77639|84207|89490|95315|102767|112213|121012|129161|139484|148901|158964|167734|171557|177530|185873|202284|222696|246927|269846|287365|302593|319324|347389|388162|437974|478570|512486|543448|565084|579965|598714|604374|597172|575887|554855|550843|547192|530800|498951|461341|413716|362597|302115|240147|186552|139829|104906|81620|65973|55619|46826|39673|33626|29186|25932|23326|20980|18661|16455|13960|11929|9959|8862|7772|7069|6352|5397|4416|3902|3121|2415|2098|1763|1478|1262|1047|947|878|725|613|473|421|334|286|191|180|125|114|95|78|50|45|34|17|19|14|12|1|4|5|5|0|1|0|0|1</HistCounts>
      </HistItem>
    </Histograms>
    <Metadata>
      <MDI key="RepresentationType">ATHEMATIC</MDI>
      <MDI key="STATISTICS_COVARIANCES">1992.541930324777,1963.06378901359,1996.770586721161</MDI>
      <MDI key="STATISTICS_EXCLUDEDVALUES"></MDI>
      <MDI key="STATISTICS_MAXIMUM">204</MDI>
      <MDI key="STATISTICS_MEAN">106.50291786495</MDI>
      <MDI key="STATISTICS_MINIMUM">0</MDI>
      <MDI key="STATISTICS_SKIPFACTORX">1</MDI>
      <MDI key="STATISTICS_SKIPFACTORY">1</MDI>
      <MDI key="STATISTICS_STDDEV">44.306475700665</MDI>
    </Metadata>
  </PAMRasterBand>
  <PAMRasterBand band="3">
    <Histograms>
      <HistItem>
        <HistMin>-0.5</HistMin>
        <HistMax>208.5</HistMax>
        <BucketCount>209</BucketCount>
        <IncludeOutOfRange>1</IncludeOutOfRange>
        <Approximate>0</Approximate>
        <HistCounts>2230923|5144|5674|6195|6733|7365|7966|8627|9607|10732|11888|13092|13953|14701|14658|14780|14491|14536|14673|14811|14856|15172|15201|15895|15739|16031|16034|16299|16589|16692|16670|16782|16911|17001|17230|17020|17284|17566|17356|17533|17594|17848|17994|17960|18453|18706|18857|19186|19541|19772|19993|20398|20900|21167|21419|21888|22014|22272|22437|22925|23319|23525|23810|23906|23982|24151|24677|24570|24964|25167|24832|25376|25854|26536|27484|29033|29923|30621|31070|30992|30381|29890|29313|28755|29103|29007|29537|30433|31451|31883|32995|34146|35275|36590|38562|40533|41727|42768|44178|45609|48703|51947|57366|63425|72983|83570|94740|106571|119777|135584|156321|182611|212021|238997|265632|296664|330545|368983|406994|447361|473367|483134|471112|442285|403330|362405|333837|309864|291507|273296|261955|257877|266399|286563|316165|342163|370938|396975|411772|414716|403170|385916|371971|352705|336251|329524|316549|297266|270369|243392|212968|184108|152716|124260|96831|75271|62744|53445|41241|27635|20404|18007|17651|18280|19565|21504|24152|26195|25525|23168|19711|16716|13759|11623|9769|8131|6834|5452|4306|3497|2700|2021|1576|1202|881|704|515|409|303|198|147|133|93|81|41|45|26|30|17|9|7|8|4|4|1|0|1|0|2</HistCounts>
      </HistItem>
    </Histograms>
    <Metadata>
      <MDI key="RepresentationType">ATHEMATIC</MDI>
      <MDI key="STATISTICS_COVARIANCES">1995.674336560615,1996.770586721161,2184.965135633967</MDI>
      <MDI key="STATISTICS_EXCLUDEDVALUES"></MDI>
      <MDI key="STATISTICS_MAXIMUM">208</MDI>
      <MDI key="STATISTICS_MEAN">108.66715474751</MDI>
      <MDI key="STATISTICS_MINIMUM">0</MDI>
      <MDI key="STATISTICS_SKIPFACTORX">1</MDI>
      <MDI key="STATISTICS_SKIPFACTORY">1</MDI>
      <MDI key="STATISTICS_STDDEV">46.74361063968</MDI>
    </Metadata>
  </PAMRasterBand>
</PAMDataset>
