<PAMDataset>
  <Metadata>
    <MDI key="DataType">Generic</MDI>
  </Metadata>
  <Metadata domain="Esri">
    <MDI key="PyramidResamplingType">NEAREST</MDI>
  </Metadata>
  <PAMRasterBand band="1">
    <Histograms>
      <HistItem>
        <HistMin>-0.5</HistMin>
        <HistMax>168.5</HistMax>
        <BucketCount>169</BucketCount>
        <IncludeOutOfRange>1</IncludeOutOfRange>
        <Approximate>0</Approximate>
        <HistCounts>2213408|311|206|1209|2682|1587|2931|2871|2489|2022|1828|1745|1568|1444|1443|1529|1276|1302|1254|1039|1010|986|868|814|864|758|727|739|685|647|564|588|562|535|497|496|495|511|493|473|466|430|468|413|407|415|418|408|418|401|420|450|415|446|406|402|382|436|354|402|381|426|379|377|398|379|392|381|363|390|384|428|441|443|422|478|546|639|791|1072|1469|2058|2807|3994|4703|6063|7302|8826|10727|12293|14201|16314|20227|24652|30657|36343|40932|45718|53737|65168|84600|105055|123662|132424|139003|146327|164815|184526|213473|235285|259828|281436|305091|329285|353718|356800|353670|338383|325659|309131|290376|267200|241995|222218|207038|183372|150198|136196|133436|138871|152860|177360|210400|241170|258984|270013|273009|273180|258838|226195|175160|117085|67477|31864|12968|6070|3517|2592|2136|1834|1514|1211|1094|885|640|466|368|262|209|147|99|70|38|19|20|9|9|4|1</HistCounts>
      </HistItem>
    </Histograms>
    <Metadata>
      <MDI key="RepresentationType">ATHEMATIC</MDI>
      <MDI key="STATISTICS_COVARIANCES">2296.268394874698,2137.99531014904,2282.246170478775</MDI>
      <MDI key="STATISTICS_EXCLUDEDVALUES"></MDI>
      <MDI key="STATISTICS_MAXIMUM">168</MDI>
      <MDI key="STATISTICS_MEAN">97.801023346184</MDI>
      <MDI key="STATISTICS_MINIMUM">0</MDI>
      <MDI key="STATISTICS_SKIPFACTORX">1</MDI>
      <MDI key="STATISTICS_SKIPFACTORY">1</MDI>
      <MDI key="STATISTICS_STDDEV">47.919394767408</MDI>
    </Metadata>
  </PAMRasterBand>
  <PAMRasterBand band="2">
    <Histograms>
      <HistItem>
        <HistMin>-0.5</HistMin>
        <HistMax>156.5</HistMax>
        <BucketCount>157</BucketCount>
        <IncludeOutOfRange>1</IncludeOutOfRange>
        <Approximate>0</Approximate>
        <HistCounts>2231629|2203|1887|1640|1529|1293|1252|1177|1138|1061|1005|957|905|792|798|719|690|682|673|617|603|578|566|553|530|519|495|558|454|452|493|473|448|436|455|416|447|487|470|410|473|409|411|445|494|477|502|444|437|413|408|407|415|444|453|483|435|458|467|498|537|589|676|730|750|841|1029|1208|1394|1699|2186|2758|3358|4639|5254|6153|7059|7610|8141|9227|11247|13635|16305|19389|23261|26743|30164|33627|38656|44751|52533|63017|78381|92578|107173|118209|126481|136841|154740|175395|198282|217973|240348|269163|295833|318479|335136|350699|358355|361776|359841|347633|329618|306667|283125|263989|254822|238381|207874|174324|160989|167241|191744|212989|226845|230949|231742|229817|227404|218614|196401|169615|127722|80772|42321|17435|6950|3391|2240|1738|1469|1257|1018|749|631|489|366|257|178|112|66|48|26|17|8|6|1</HistCounts>
      </HistItem>
    </Histograms>
    <Metadata>
      <MDI key="RepresentationType">ATHEMATIC</MDI>
      <MDI key="STATISTICS_COVARIANCES">2137.99531014904,1998.505256817615,2134.946534328345</MDI>
      <MDI key="STATISTICS_EXCLUDEDVALUES"></MDI>
      <MDI key="STATISTICS_MAXIMUM">156</MDI>
      <MDI key="STATISTICS_MEAN">90.914927897094</MDI>
      <MDI key="STATISTICS_MINIMUM">0</MDI>
      <MDI key="STATISTICS_SKIPFACTORX">1</MDI>
      <MDI key="STATISTICS_SKIPFACTORY">1</MDI>
      <MDI key="STATISTICS_STDDEV">44.704644689535</MDI>
    </Metadata>
  </PAMRasterBand>
  <PAMRasterBand band="3">
    <Histograms>
      <HistItem>
        <HistMin>-0.5</HistMin>
        <HistMax>159.5</HistMax>
        <BucketCount>160</BucketCount>
        <IncludeOutOfRange>1</IncludeOutOfRange>
        <Approximate>0</Approximate>
        <HistCounts>2220366|1742|3004|2053|2742|2649|2118|1945|1730|1573|1431|1308|1181|1056|1018|989|947|795|792|778|722|654|641|654|562|589|507|546|535|477|517|504|470|455|474|463|472|426|467|419|472|473|440|434|434|448|461|432|436|446|425|473|437|482|464|463|529|523|527|576|609|627|656|689|707|749|758|803|811|878|907|948|1029|1094|1149|1227|1314|1498|1701|1915|2141|2428|2562|2883|3331|3525|3721|4109|4158|4199|4301|4278|4267|4315|4509|4775|5194|6011|7260|8533|10407|12500|14763|18002|22571|29079|37072|47819|59922|72520|83545|96851|110885|130168|155066|185247|222850|266584|312038|358171|401914|451288|486390|514677|518633|524258|522970|536256|532301|522989|483356|421369|351314|291234|251138|218785|178895|130971|90255|52630|29867|15296|7738|3851|1924|1087|712|439|314|232|179|102|94|52|30|20|13|7|1|6</HistCounts>
      </HistItem>
    </Histograms>
    <Metadata>
      <MDI key="RepresentationType">ATHEMATIC</MDI>
      <MDI key="STATISTICS_COVARIANCES">2282.246170478775,2134.946534328345,2379.952208917028</MDI>
      <MDI key="STATISTICS_EXCLUDEDVALUES"></MDI>
      <MDI key="STATISTICS_MAXIMUM">159</MDI>
      <MDI key="STATISTICS_MEAN">101.04938690794</MDI>
      <MDI key="STATISTICS_MINIMUM">0</MDI>
      <MDI key="STATISTICS_SKIPFACTORX">1</MDI>
      <MDI key="STATISTICS_SKIPFACTORY">1</MDI>
      <MDI key="STATISTICS_STDDEV">48.784753857297</MDI>
    </Metadata>
  </PAMRasterBand>
</PAMDataset>
