<PAMDataset>
  <Metadata>
    <MDI key="DataType">Generic</MDI>
  </Metadata>
  <Metadata domain="Esri">
    <MDI key="PyramidResamplingType">NEAREST</MDI>
  </Metadata>
  <PAMRasterBand band="1">
    <Histograms>
      <HistItem>
        <HistMin>-0.5</HistMin>
        <HistMax>201.5</HistMax>
        <BucketCount>202</BucketCount>
        <IncludeOutOfRange>1</IncludeOutOfRange>
        <Approximate>0</Approximate>
        <HistCounts>2588400|5|4|32|200|121|398|529|535|497|548|556|575|582|660|640|597|644|657|669|624|656|652|622|639|599|611|568|543|537|544|558|530|490|463|492|502|457|492|520|434|491|480|455|437|413|414|401|399|364|419|387|388|436|396|385|420|403|399|412|476|557|785|1057|1448|1753|2139|2748|3409|4116|4714|5455|6240|7896|9398|10785|12083|13314|14424|15708|16905|18999|21360|22550|22606|23476|24429|24621|25250|27393|29522|32934|37022|42916|47469|52580|57023|63321|72210|86494|101993|121733|135639|144187|150185|155490|161683|173892|182724|194013|201685|208858|213996|221956|234360|252150|267944|287725|308211|336253|353045|370020|377141|389717|393539|406677|396610|380226|367959|363046|340145|303832|265949|233169|209158|178210|148295|131006|132515|147536|161590|170465|174286|170562|166232|154840|124943|80377|44955|22740|12875|9156|7132|6243|5445|4782|4065|3242|2753|2240|1911|1529|1420|1146|1082|948|771|720|579|498|480|399|333|306|274|219|171|184|122|119|95|71|68|48|38|26|17|22|9|17|9|8|6|3|1|2|5|3|1|0|2|4</HistCounts>
      </HistItem>
    </Histograms>
    <Metadata>
      <MDI key="RepresentationType">ATHEMATIC</MDI>
      <MDI key="STATISTICS_COVARIANCES">2310.819944032214,2176.889376484262,2192.144050570191</MDI>
      <MDI key="STATISTICS_EXCLUDEDVALUES"></MDI>
      <MDI key="STATISTICS_MAXIMUM">201</MDI>
      <MDI key="STATISTICS_MEAN">99.883547464222</MDI>
      <MDI key="STATISTICS_MEDIAN">119.000000</MDI>
      <MDI key="STATISTICS_MINIMUM">0</MDI>
      <MDI key="STATISTICS_SKIPFACTORX">1</MDI>
      <MDI key="STATISTICS_SKIPFACTORY">1</MDI>
      <MDI key="STATISTICS_STDDEV">48.070988590128</MDI>
    </Metadata>
  </PAMRasterBand>
  <PAMRasterBand band="2">
    <Histograms>
      <HistItem>
        <HistMin>-0.5</HistMin>
        <HistMax>193.5</HistMax>
        <BucketCount>194</BucketCount>
        <IncludeOutOfRange>1</IncludeOutOfRange>
        <Approximate>0</Approximate>
        <HistCounts>2590710|680|676|652|640|706|663|668|679|719|743|669|657|687|630|685|603|582|570|568|550|559|580|489|554|463|505|498|457|445|454|471|474|464|465|441|417|449|421|457|375|427|374|417|410|402|385|434|386|427|417|429|471|507|689|900|1280|1738|2092|2617|3200|3663|4209|5022|6028|7461|8751|10449|11232|12077|12371|13096|14302|16444|18647|20443|21649|23229|23338|23407|24749|27353|29846|33367|37475|43020|47011|50655|54939|60104|67381|78267|92090|107373|119972|125785|127114|127498|135206|149500|166658|181023|192874|201568|208927|213651|218409|229278|244229|266584|290942|317942|344605|363124|378054|397860|414816|437032|435599|411897|383656|367022|361561|354032|323300|282878|245632|216664|198363|182873|169851|159891|155123|153883|153644|152975|148593|126255|87891|56145|32086|19809|14757|12249|10374|8526|7551|6482|5601|4741|4201|3657|3032|2461|2025|1676|1325|1093|935|802|728|655|550|476|370|323|258|222|191|148|124|86|94|77|57|34|31|20|19|17|17|14|4|5|4|3|2|2|3|2|1|0|2|1</HistCounts>
      </HistItem>
    </Histograms>
    <Metadata>
      <MDI key="RepresentationType">ATHEMATIC</MDI>
      <MDI key="STATISTICS_COVARIANCES">2176.889376484262,2054.413910796988,2070.682055130642</MDI>
      <MDI key="STATISTICS_EXCLUDEDVALUES"></MDI>
      <MDI key="STATISTICS_MAXIMUM">193</MDI>
      <MDI key="STATISTICS_MEAN">93.814104640104</MDI>
      <MDI key="STATISTICS_MEDIAN">112.000000</MDI>
      <MDI key="STATISTICS_MINIMUM">0</MDI>
      <MDI key="STATISTICS_SKIPFACTORX">1</MDI>
      <MDI key="STATISTICS_SKIPFACTORY">1</MDI>
      <MDI key="STATISTICS_STDDEV">45.325642971689</MDI>
    </Metadata>
  </PAMRasterBand>
  <PAMRasterBand band="3">
    <Histograms>
      <HistItem>
        <HistMin>-0.5</HistMin>
        <HistMax>192.5</HistMax>
        <BucketCount>193</BucketCount>
        <IncludeOutOfRange>1</IncludeOutOfRange>
        <Approximate>0</Approximate>
        <HistCounts>2593797|739|713|726|768|735|735|697|705|687|684|611|605|599|617|554|540|551|538|521|493|551|482|514|514|486|496|438|472|444|505|463|412|419|427|413|407|402|365|415|436|433|408|397|380|387|398|403|404|398|394|401|400|462|433|415|431|393|448|478|488|584|736|1055|1464|2007|2400|3138|3617|4460|5331|6365|7230|7877|8722|9794|11073|12316|13753|14705|16117|17235|17759|18645|19788|20856|22242|24398|26933|29425|31751|33842|36965|41618|47816|55506|63359|72145|83280|96007|112797|132556|152650|169047|178501|190056|201369|217982|229084|243300|256181|269651|280049|291243|299931|317527|335090|358882|382114|409605|418635|424821|426342|421622|411383|405343|421742|447474|460412|440831|399697|342621|285215|222680|155783|97904|61014|43252|36346|29513|21202|16597|14550|14850|15945|17298|19391|20454|20704|18823|16778|14009|11482|9455|7675|6519|5248|4457|3621|2945|2246|1787|1368|1051|823|680|541|402|310|253|197|181|133|97|72|40|32|34|29|17|7|15|5|4|2|1|2|4|1|2|1|0|1</HistCounts>
      </HistItem>
    </Histograms>
    <Metadata>
      <MDI key="RepresentationType">ATHEMATIC</MDI>
      <MDI key="STATISTICS_COVARIANCES">2192.144050570191,2070.682055130642,2163.500078901625</MDI>
      <MDI key="STATISTICS_EXCLUDEDVALUES"></MDI>
      <MDI key="STATISTICS_MAXIMUM">192</MDI>
      <MDI key="STATISTICS_MEAN">97.229552898464</MDI>
      <MDI key="STATISTICS_MEDIAN">116.000000</MDI>
      <MDI key="STATISTICS_MINIMUM">0</MDI>
      <MDI key="STATISTICS_SKIPFACTORX">1</MDI>
      <MDI key="STATISTICS_SKIPFACTORY">1</MDI>
      <MDI key="STATISTICS_STDDEV">46.51343976639</MDI>
    </Metadata>
  </PAMRasterBand>
</PAMDataset>
